{
  "context_experiment": {
    "image_dims": [
      8,
      16,
      32,
      64,
      128
    ]
  },
  "evaluation": {
    "folds": 5,
    "metrics": [
      "accuracy",
      "precision",
      "recall",
      "f1"
    ]
  },
  "model": {
    "model_name": "model_1",
    "model_type": "cnn",
    "num_classes": 2
  },
  "nodule_dataset": {
    "consensus_level": 0.5,
    "image_dim": 64,
    "n_cv_folds": 5,
    "normalisation_bounds": [
      -1000,
      400
    ],
    "segment_nodule": "remove_background"
  },
  "training": {
    "batch_size": 32,
    "epoch_print_interval": 10,
    "lr": 0.001,
    "num_epochs": 10
  }
}
