{"config_name": "c60_3D", "id": "c60_3D_2511_2027", "start_time": "2024-11-25 20:27:03.103293", "duration": null, "dataset": {"context_window": 60, "clipping_bounds": [-1000, 400], "segment_nodule": "none", "dimensionality": "3D", "data_augmentation": true}, "model": {"num_classes": 5, "in_channels": 1}, "training": {"batch_size": 8, "learning_rate": 0.001, "num_epochs": 100, "dropout_rate": 0.3, "do_cross_validation": true, "cross_validation_folds": 5, "cv_train_folds": 5, "num_workers": 8, "patience": 30, "min_delta": 0.01, "gpu_used": "Tesla V100-PCIE-32GB"}, "fold_results": []}